{
  "Images/Banners\\UnknownLibrary.png": "2025-08-09T01:12:38+01:00",
  "Images/Banners\\PlatformName\\Android.png": "2025-08-09T01:12:38+01:00",
  "Images/Banners\\PlatformName\\Arcade.png": "2025-08-09T01:12:38+01:00",
  "Images/Banners\\PlatformName\\iOS.png": "2025-08-09T01:12:38+01:00",
  "Images/Banners\\PlatformName\\Microsoft MSX.png": "2025-08-09T01:12:38+01:00",
  "Images/Banners\\PlatformName\\Microsoft MSX2.png": "2025-08-09T01:12:38+01:00",
  "Images/Banners\\PlatformName\\NEC PC-9801.png": "2025-08-09T01:12:38+01:00",
  "Images/Banners\\PlatformName\\Philips CD-i.png": "2025-08-09T01:12:38+01:00",
  "Images/Banners\\PlatformName\\PICO-8.png": "2025-08-09T01:12:38+01:00",
  "Images/Banners\\PlatformName\\Sega NAOMI.png": "2025-08-09T01:12:38+01:00",
  "Images/Banners\\PlatformName\\Web.png": "2025-08-09T01:12:38+01:00",
  "Images/Banners\\PlatformSpecId\\3do.png": "2025-08-09T01:12:38+01:00",
  "Images/Banners\\PlatformSpecId\\adobe_flash.png": "2025-08-09T01:12:38+01:00",
  "Images/Banners\\PlatformSpecId\\amstrad_cpc.png": "2025-08-09T01:12:38+01:00",
  "Images/Banners\\PlatformSpecId\\apple_2.jpg": "2025-08-09T01:12:38+01:00",
  "Images/Banners\\PlatformSpecId\\atari_2600.png": "2025-08-09T01:12:38+01:00",
  "Images/Banners\\PlatformSpecId\\atari_5200.png": "2025-08-09T01:12:38+01:00",
  "Images/Banners\\PlatformSpecId\\atari_7800.png": "2025-08-09T01:12:38+01:00",
  "Images/Banners\\PlatformSpecId\\atari_jaguar.png": "2025-08-09T01:12:38+01:00",
  "Images/Banners\\PlatformSpecId\\atari_lynx.png": "2025-08-09T01:12:38+01:00",
  "Images/Banners\\PlatformSpecId\\bandai_wonderswan.png": "2025-08-09T01:12:38+01:00",
  "Images/Banners\\PlatformSpecId\\bandai_wonderswan_color.png": "2025-08-09T01:12:38+01:00",
  "Images/Banners\\PlatformSpecId\\coleco_vision.png": "2025-08-09T01:12:38+01:00",
  "Images/Banners\\PlatformSpecId\\commodore_64.png": "2025-08-09T01:12:38+01:00",
  "Images/Banners\\PlatformSpecId\\commodore_amiga.png": "2025-08-09T01:12:38+01:00",
  "Images/Banners\\PlatformSpecId\\commodore_amiga_cd32.png": "2025-08-09T01:12:38+01:00",
  "Images/Banners\\PlatformSpecId\\macintosh.jpg": "2025-08-09T01:12:38+01:00",
  "Images/Banners\\PlatformSpecId\\mattel_intellivision.png": "2025-08-09T01:12:38+01:00",
  "Images/Banners\\PlatformSpecId\\nec_pcfx.png": "2025-08-09T01:12:38+01:00",
  "Images/Banners\\PlatformSpecId\\nec_supergrafx.png": "2025-08-09T01:12:38+01:00",
  "Images/Banners\\PlatformSpecId\\nec_turbografx_16.png": "2025-08-09T01:12:38+01:00",
  "Images/Banners\\PlatformSpecId\\nec_turbografx_cd.png": "2025-08-09T01:12:38+01:00",
  "Images/Banners\\PlatformSpecId\\nintendo_3ds.png": "2025-08-09T01:12:38+01:00",
  "Images/Banners\\PlatformSpecId\\nintendo_64.jpg": "2025-08-09T01:12:38+01:00",
  "Images/Banners\\PlatformSpecId\\nintendo_ds.jpg": "2025-08-09T01:12:38+01:00",
  "Images/Banners\\PlatformSpecId\\nintendo_famicom_disk.png": "2025-08-09T01:12:38+01:00",
  "Images/Banners\\PlatformSpecId\\nintendo_gameboy.jpg": "2025-08-09T01:12:38+01:00",
  "Images/Banners\\PlatformSpecId\\nintendo_gameboyadvance.png": "2025-08-09T01:12:38+01:00",
  "Images/Banners\\PlatformSpecId\\nintendo_gameboycolor.png": "2025-08-09T01:12:38+01:00",
  "Images/Banners\\PlatformSpecId\\nintendo_gamecube.png": "2025-08-09T01:12:38+01:00",
  "Images/Banners\\PlatformSpecId\\nintendo_nes.png": "2025-08-09T01:12:38+01:00",
  "Images/Banners\\PlatformSpecId\\nintendo_super_nes.png": "2025-08-09T01:12:38+01:00",
  "Images/Banners\\PlatformSpecId\\nintendo_switch.jpg": "2025-08-09T01:12:38+01:00",
  "Images/Banners\\PlatformSpecId\\nintendo_virtualboy.png": "2025-08-09T01:12:38+01:00",
  "Images/Banners\\PlatformSpecId\\nintendo_wii.png": "2025-08-09T01:12:38+01:00",
  "Images/Banners\\PlatformSpecId\\nintendo_wiiu.jpg": "2025-08-09T01:12:38+01:00",
  "Images/Banners\\PlatformSpecId\\pc_dos.png": "2025-08-09T01:12:38+01:00",
  "Images/Banners\\PlatformSpecId\\pc_windows.png": "2025-08-09T01:12:38+01:00",
  "Images/Banners\\PlatformSpecId\\sega_32x.png": "2025-08-09T01:12:38+01:00",
  "Images/Banners\\PlatformSpecId\\sega_cd.png": "2025-08-09T01:12:38+01:00",
  "Images/Banners\\PlatformSpecId\\sega_dreamcast.png": "2025-08-09T01:12:38+01:00",
  "Images/Banners\\PlatformSpecId\\sega_gamegear.png": "2025-08-09T01:12:38+01:00",
  "Images/Banners\\PlatformSpecId\\sega_genesis.png": "2025-08-09T01:12:38+01:00",
  "Images/Banners\\PlatformSpecId\\sega_mastersystem.png": "2025-08-09T01:12:38+01:00",
  "Images/Banners\\PlatformSpecId\\sega_saturn.png": "2025-08-09T01:12:38+01:00",
  "Images/Banners\\PlatformSpecId\\sinclair_zxspectrum.png": "2025-08-09T01:12:38+01:00",
  "Images/Banners\\PlatformSpecId\\snk_neogeopocket.png": "2025-08-09T01:12:38+01:00",
  "Images/Banners\\PlatformSpecId\\snk_neogeopocket_color.png": "2025-08-09T01:12:38+01:00",
  "Images/Banners\\PlatformSpecId\\sony_playstation.jpg": "2025-08-09T01:12:38+01:00",
  "Images/Banners\\PlatformSpecId\\sony_playstation2.jpg": "2025-08-09T01:12:38+01:00",
  "Images/Banners\\PlatformSpecId\\sony_playstation3.jpg": "2025-08-09T01:12:38+01:00",
  "Images/Banners\\PlatformSpecId\\sony_playstation4.jpg": "2025-08-09T01:12:38+01:00",
  "Images/Banners\\PlatformSpecId\\sony_playstation5.jpg": "2025-08-09T01:12:38+01:00",
  "Images/Banners\\PlatformSpecId\\sony_psp.png": "2025-08-09T01:12:38+01:00",
  "Images/Banners\\PlatformSpecId\\sony_vita.jpg": "2025-08-09T01:12:38+01:00",
  "Images/Banners\\PlatformSpecId\\vectrex.png": "2025-08-09T01:12:38+01:00",
  "Images/Banners\\PlatformSpecId\\xbox.jpg": "2025-08-09T01:12:38+01:00",
  "Images/Banners\\PlatformSpecId\\xbox360.jpg": "2025-08-09T01:12:38+01:00",
  "Images/Banners\\PlatformSpecId\\xbox_one.jpg": "2025-08-09T01:12:38+01:00",
  "Images/Banners\\PlatformSpecId\\xbox_series.png": "2025-08-09T01:12:38+01:00",
  "Images/Banners\\PluginId\\00000000-0000-0000-0000-000000000000.png": "2025-08-09T01:12:38+01:00",
  "Images/Banners\\PluginId\\00000001-ebb2-4eec-abcb-7c89937a42bb.png": "2025-08-09T01:12:38+01:00",
  "Images/Banners\\PluginId\\00000002-dbd1-46c6-b5d0-b1ba559d10e4.jpg": "2025-08-09T01:12:38+01:00",
  "Images/Banners\\PluginId\\03689811-3f33-4dfb-a121-2ee168fb9a5c.png": "2025-08-09T01:12:38+01:00",
  "Images/Banners\\PluginId\\0dbead64-b7ed-47e5-904c-0ccdb5d5ff59.png": "2025-08-09T01:12:38+01:00",
  "Images/Banners\\PluginId\\0e2e793e-e0dd-4447-835c-c44a1fd506ec.png": "2025-08-09T01:12:38+01:00",
  "Images/Banners\\PluginId\\2366fb38-bf25-45ea-9a78-dcc797ee83c3.png": "2025-08-09T01:12:38+01:00",
  "Images/Banners\\PluginId\\2a62a584-2cc3-4220-8da6-cf4ac588a439.png": "2025-08-09T01:12:38+01:00",
  "Images/Banners\\PluginId\\317a5e2e-eac1-48bc-adb3-fb9e321afd3f.png": "2025-08-09T01:12:38+01:00",
  "Images/Banners\\PluginId\\34c3178f-6e1d-4e27-8885-99d4f031b168.png": "2025-08-09T01:12:38+01:00",
  "Images/Banners\\PluginId\\37995df7-2ce2-4f7c-83a3-618138ae745d.png": "2025-08-09T01:12:38+01:00",
  "Images/Banners\\PluginId\\402674cd-4af6-4886-b6ec-0e695bfa0688.png": "2025-08-09T01:12:38+01:00",
  "Images/Banners\\PluginId\\40e56f44-4955-40ec-9bf3-682c4007e55b.png": "2025-08-09T01:12:38+01:00",
  "Images/Banners\\PluginId\\41e49490-0583-4148-94d2-940c7c74f1d9.png": "2025-08-09T01:12:38+01:00",
  "Images/Banners\\PluginId\\42ff71aa-34dc-4b12-86b6-1328136c958f.png": "2025-08-09T01:12:38+01:00",
  "Images/Banners\\PluginId\\4de579c6-7179-4229-b776-7a3a9e902052.png": "2025-08-09T01:12:38+01:00",
  "Images/Banners\\PluginId\\555d58fd-a000-401b-972c-9230bed81aed.png": "2025-08-09T01:12:38+01:00",
  "Images/Banners\\PluginId\\5901b4b4-774d-411a-9cce-807c5ca49d88.png": "2025-08-09T01:12:38+01:00",
  "Images/Banners\\PluginId\\5befaf7a-a0af-4ce2-992c-bc048d94e71b.jpg": "2025-08-09T01:12:38+01:00",
  "Images/Banners\\PluginId\\5f2dfd12-5f13-46fe-bcdd-64eb53ace26a.png": "2025-08-09T01:12:38+01:00",
  "Images/Banners\\PluginId\\62ac4052-e08a-4a1a-b70a-c2c0c3673bb9.png": "2025-08-09T01:12:38+01:00",
  "Images/Banners\\PluginId\\6ab2531e-4800-404b-a938-4421b28a9f3e.png": "2025-08-09T01:12:38+01:00",
  "Images/Banners\\PluginId\\77346dd6-b0cc-4f7d-80f0-c1d138ccae58.png": "2025-08-09T01:12:38+01:00",
  "Images/Banners\\PluginId\\7e4fbb5e-2ae3-48d4-8ba0-6b30e7a4e287.jpg": "2025-08-09T01:12:38+01:00",
  "Images/Banners\\PluginId\\85dd7072-2f20-4e76-a007-41035e390724.png": "2025-08-09T01:12:38+01:00",
  "Images/Banners\\PluginId\\88409022-088a-4de8-805a-fdbac291f00a.png": "2025-08-09T01:12:38+01:00",
  "Images/Banners\\PluginId\\91d13c6f-63d3-42ed-a100-6f811a8387ea.png": "2025-08-09T01:12:38+01:00",
  "Images/Banners\\PluginId\\96e8c4bc-ec5c-4c8b-87e7-18ee5a690626.png": "2025-08-09T01:12:38+01:00",
  "Images/Banners\\PluginId\\9700aa21-447d-41b4-a989-acd38f407d9f.png": "2025-08-09T01:12:38+01:00",
  "Images/Banners\\PluginId\\97d85dbd-ad52-4834-bf4b-f6681f1445cc.png": "2025-08-09T01:12:38+01:00",
  "Images/Banners\\PluginId\\a8050aa6-0fb3-4b28-8bac-491d644e81c7.png": "2025-08-09T01:12:38+01:00",
  "Images/Banners\\PluginId\\aebe8b7c-6dc3-4a66-af31-e7375c6b5e9e.png": "2025-08-09T01:12:38+01:00",
  "Images/Banners\\PluginId\\b28970a8-37b0-4461-aa33-628024643e73.png": "2025-08-09T01:12:38+01:00",
  "Images/Banners\\PluginId\\c2f038e5-8b92-4877-91f1-da9094155fc5.png": "2025-08-09T01:12:38+01:00",
  "Images/Banners\\PluginId\\cb91dfc9-b977-43bf-8e70-55f46e410fab.png": "2025-08-09T01:12:38+01:00",
  "Images/Banners\\PluginId\\d407a620-5953-4ca4-a25c-8194c8559381.png": "2025-08-09T01:12:38+01:00",
  "Images/Banners\\PluginId\\e3c26a3d-d695-4cb7-a769-5ff7612c7edd.png": "2025-08-09T01:12:38+01:00",
  "Images/Banners\\PluginId\\e4ac81cb-1b1a-4ec9-8639-9a9633989a71.jpg": "2025-08-09T01:12:38+01:00",
  "Images/Banners\\PluginId\\e4ac81cb-1b1a-4ec9-8639-9a9633989a72.png": "2025-08-09T01:12:38+01:00",
  "Images/Banners\\PluginId\\e894b739-2d6e-41ee-aed4-2ea898e29803.png": "2025-08-09T01:12:38+01:00",
  "Images/Banners\\PluginId\\ead65c3b-2f8f-4e37-b4e6-b3de6be540c6.png": "2025-08-09T01:12:38+01:00",
  "Images/Banners\\PluginId\\ef17cc27-95d4-45e7-bd49-214ba2e5f4b2.png": "2025-08-09T01:12:38+01:00",
  "Images/Banners\\PluginId\\f7da6eb0-17d7-497c-92fd-347050914954.png": "2025-08-09T01:12:38+01:00",
  "Images/Banners\\PluginId\\faaf4c1f-14ca-487e-8f32-d7a40c6b9c9a.png": "2025-09-25T12:17:04+01:00",
  "Images/Banners\\PluginId\\fab8be77-18ab-4e6c-ad3d-89097b492d74.png": "2025-08-09T01:12:38+01:00",
  "Images/Banners\\PluginId\\fcd1bbc9-c3a3-499f-9a4c-8b7c9c8b9de8.png": "2025-08-09T01:12:38+01:00",
  "Images/Banners\\SourceName\\Microsoft Store.png": "2025-08-09T01:12:38+01:00",
  "Images/Banners\\SourceName\\Steam.png": "2025-05-30T12:13:08+01:00"
}